driver/__init__.py
driver/driver.py
terminaltruck-0.1.8.dist-info/METADATA
terminaltruck-0.1.8.dist-info/WHEEL
terminaltruck-0.1.8.dist-info/top_level.txt
terminaltruck-0.1.8.dist-info/RECORD
