Metadata-Version: 2.4
Name: terminaltruck
Version: 0.1.8
Summary: Game about trucking
Home-page: https://github.com/Viktor640266/driver
Author: Vitek
Author-email: Vitek <cheeseqwertycheese@gmail.com>
License: MIT
Project-URL: Homepage, https://github.com/Viktor640266/driver
Classifier: Programming Language :: Python :: 3
Classifier: License :: OSI Approved :: MIT License
Classifier: Operating System :: OS Independent
Requires-Python: >=3.7
Dynamic: author
Dynamic: home-page
Dynamic: requires-python
